removeurl
